backpack_checker/__about__.py
backpack_checker/__init__.py
backpack_checker/app.py
backpack_checker/checker.py
backpack_checker/default.tcss
backpack_checker/log_handler.py
backpack_checker-0.1.0.dist-info/METADATA
backpack_checker-0.1.0.dist-info/WHEEL
backpack_checker-0.1.0.dist-info/entry_points.txt
backpack_checker-0.1.0.dist-info/RECORD
