Metadata-Version: 2.4
Name: backpack-checker
Version: 0.1.0
Summary: A tool to check the status of your "backpack", "backpack" being your local setup for a project.
Project-URL: Issues, https://github.com/pkucmus/backpack/issues
Project-URL: Source, https://github.com/pkucmus/backpack
Author-email: Paweł Kucmus <pkucmus@gmail.com>
License-Expression: BSD-3-Clause
Classifier: Development Status :: 4 - Beta
Classifier: Environment :: Console
Classifier: Intended Audience :: Developers
Classifier: Programming Language :: Python
Classifier: Programming Language :: Python :: 3.12
Classifier: Programming Language :: Python :: 3.13
Classifier: Programming Language :: Python :: Implementation :: CPython
Classifier: Topic :: Software Development
Classifier: Topic :: Software Development :: Libraries :: Python Modules
Requires-Python: >=3.12
Requires-Dist: docker>=7.1.0
Requires-Dist: semver>=3.0.2
Requires-Dist: textual>=1.0.0
Provides-Extra: dev
Requires-Dist: ipdb>=0.13.13; extra == 'dev'
Requires-Dist: ipython>=8.31.0; extra == 'dev'
Requires-Dist: mypy>=1.14.0; extra == 'dev'
Requires-Dist: textual-dev>=1.7.0; extra == 'dev'
Provides-Extra: types
Requires-Dist: mypy>=1.0.0; extra == 'types'
Requires-Dist: pytest; extra == 'types'
Requires-Dist: pytest-asyncio; extra == 'types'
Requires-Dist: types-toml; extra == 'types'
